dlna_cli/__init__.py
dlna_cli/__main__.py
dlna_cli/api.py
dlna_cli/api_factory.py
dlna_cli/upnp_device.py
dlna_cli-0.1.1.dist-info/entry_points.txt
dlna_cli-0.1.1.dist-info/WHEEL
dlna_cli-0.1.1.dist-info/METADATA
dlna_cli-0.1.1.dist-info/RECORD
