Metadata-Version: 2.1
Name: dlna-cli
Version: 0.1.1
Summary: 
Author: Daniel Daniels
Author-email: danields761@gmail.com
Requires-Python: >=3.8,<4.0
Classifier: Programming Language :: Python :: 3
Classifier: Programming Language :: Python :: 3.8
Requires-Dist: click (>=7.1.2,<8.0.0)
Requires-Dist: colorama (>=0.4.3,<0.5.0)
Requires-Dist: pydantic (>=1.5.1,<2.0.0)
Requires-Dist: stringcase (>=1.2.0,<2.0.0)
Requires-Dist: termcolor (>=1.1.0,<2.0.0)
Requires-Dist: upnpclient (>=0.0.8,<0.0.9)
